{
  "configurations": [
    {
      "name": "Linux-ARM64",
      "generator": "Ninja",
      "configurationType": "Release",
      "cmakeExecutable": "cmake",
      "remoteCopySourcesExclusionList": [ ".vs", ".git", "out" ],
      "cmakeCommandArgs": "",
      "buildCommandArgs": "",
      "ctestCommandArgs": "",
      "inheritEnvironments": [ "linux_arm" ],
      "remoteMachineName": "782879736;192.168.0.50 (username=pi, port=22, authentication=Password)",
      "remoteCMakeListsRoot": "$HOME/.vs/${projectDirName}/${workspaceHash}/src",
      "remoteBuildRoot": "$HOME/programs/ROV",
      "remoteInstallRoot": "$HOME/.vs/${projectDirName}/${workspaceHash}/out/install/${name}",
      "remoteCopySources": true,
      "rsyncCommandArgs": "-t --delete --delete-excluded",
      "remoteCopyBuildOutput": false,
      "remoteCopySourcesMethod": "rsync",
      "addressSanitizerRuntimeFlags": "detect_leaks=0",
      "variables": []
    },
    {
      "name": "WSL-GCC-Release",
      "generator": "Ninja",
      "configurationType": "Release",
      "buildRoot": "${projectDir}\\out\\build\\${name}",
      "installRoot": "${projectDir}\\out\\install\\${name}",
      "cmakeExecutable": "cmake",
      "cmakeCommandArgs": "",
      "buildCommandArgs": "",
      "ctestCommandArgs": "",
      "inheritEnvironments": [ "linux_x64" ],
      "wslPath": "C:\\Users\\flesmot\\AppData\\Local\\Microsoft\\WindowsApps\\debian.exe",
      "addressSanitizerRuntimeFlags": "detect_leaks=0",
      "variables": []
    }
  ]
}